columns_gpt/__init__.py
columns_gpt/analyzer.py
columns_gpt/cli.py
columns_gpt/llm.py
columns_gpt/models.py
columns_gpt/prompts.py
columns_gpt/utils.py
columns_gpt/config/__init__.py
columns_gpt/examples/__init__.py
columns_gpt/examples/basic_usage.py
columns_gpt/tests/__init__.py
columns_gpt/tests/test_utils.py
columns_gpt-0.1.2.dist-info/LICENSE
columns_gpt-0.1.2.dist-info/METADATA
columns_gpt-0.1.2.dist-info/WHEEL
columns_gpt-0.1.2.dist-info/entry_points.txt
columns_gpt-0.1.2.dist-info/top_level.txt
columns_gpt-0.1.2.dist-info/RECORD
