Metadata-Version: 2.2
Name: columns-gpt
Version: 0.1.2
Summary: DataFrame column analysis and matching with LLM
Home-page: https://github.com/zen-apps/columns-gpt
Author: Josh Janzen
Author-email: Josh Janzen <joshjanzen@gmail.com>
License: MIT
Project-URL: Homepage, https://github.com/zen-apps/columns-gpt
Project-URL: Repository, https://github.com/zen-apps/columns-gpt.git
Project-URL: Bug Tracker, https://github.com/zen-apps/columns-gpt/issues
Classifier: Development Status :: 3 - Alpha
Classifier: Intended Audience :: Developers
Classifier: Intended Audience :: Science/Research
Classifier: License :: OSI Approved :: MIT License
Classifier: Programming Language :: Python :: 3.8
Classifier: Programming Language :: Python :: 3.9
Classifier: Programming Language :: Python :: 3.10
Classifier: Programming Language :: Python :: 3.11
Classifier: Topic :: Scientific/Engineering :: Artificial Intelligence
Classifier: Topic :: Scientific/Engineering :: Information Analysis
Requires-Python: >=3.8
License-File: LICENSE
Dynamic: author
Dynamic: home-page
Dynamic: requires-python
